{
  "records": [
    {
      "date": "2026-07-07",
      "totalMl": 900,
      "logs": [
        {
          "time": "16:33",
          "ml": 500
        },
        {
          "time": "16:33",
          "ml": 200
        },
        {
          "time": "16:38",
          "ml": 200
        }
      ]
    },
    {
      "date": "2026-07-08",
      "totalMl": 1000,
      "logs": [
        {
          "id": "mrbuh0hdpgygot",
          "time": "16:57",
          "ml": 500
        },
        {
          "id": "mrbuh2otahbsoc",
          "time": "16:57",
          "ml": 500
        }
      ]
    }
  ]
}